ez_setup.py
setup.py
base36/__init__.py
base36/_version.py
base36/base36.py
base36/test/__init__.py
base36/test/test_base36.py
z_base_36.egg-info/PKG-INFO
z_base_36.egg-info/SOURCES.txt
z_base_36.egg-info/dependency_links.txt
z_base_36.egg-info/not-zip-safe
z_base_36.egg-info/requires.txt
z_base_36.egg-info/top_level.txt